twitch/__init__.py
twitch/client.py
twitch/conf.py
twitch/constants.py
twitch/decorators.py
twitch/exceptions.py
twitch/resources.py
twitch/api/__init__.py
twitch/api/base.py
twitch/api/channel_feed.py
twitch/api/channels.py
twitch/api/chat.py
twitch/api/clips.py
twitch/api/collections.py
twitch/api/communities.py
twitch/api/games.py
twitch/api/ingests.py
twitch/api/search.py
twitch/api/streams.py
twitch/api/teams.py
twitch/api/users.py
twitch/api/videos.py
twitch/helix/__init__.py
twitch/helix/api.py
twitch/helix/base.py
python_twitch_client-0.7.1.dist-info/LICENSE
python_twitch_client-0.7.1.dist-info/METADATA
python_twitch_client-0.7.1.dist-info/WHEEL
python_twitch_client-0.7.1.dist-info/top_level.txt
python_twitch_client-0.7.1.dist-info/RECORD
