Metadata-Version: 2.1
Name: python-twitch-client
Version: 0.7.1
Summary: Easy to use Python library for accessing the Twitch API
Home-page: https://github.com/tsifrer/python-twitch-client
Author: Tomaz Sifrer
Author-email: tomazz.sifrer@gmail.com
License: MIT
Platform: UNKNOWN
Classifier: Intended Audience :: Developers
Classifier: License :: OSI Approved :: MIT License
Classifier: Natural Language :: English
Classifier: Programming Language :: Python :: 3
Classifier: Programming Language :: Python :: 3.6
Classifier: Programming Language :: Python :: 3.7
Classifier: Programming Language :: Python :: 3.8
Classifier: Topic :: Internet
Classifier: Topic :: Software Development :: Libraries :: Python Modules
Requires-Python: >=3.6, <4
Provides-Extra: doc
Provides-Extra: test
